tinrun/__init__.py
tinrun/__main__.py
tinrun/bam2gtf.py
tinrun/main.py
tinrun/overlap.py
tinrun/tin.py
tincheck-0.3.0.dist-info/METADATA
tincheck-0.3.0.dist-info/WHEEL
tincheck-0.3.0.dist-info/entry_points.txt
tincheck-0.3.0.dist-info/top_level.txt
tincheck-0.3.0.dist-info/RECORD
