Metadata-Version: 2.1
Name: tincheck
Version: 0.3.0
Summary: tincheck
Home-page: https://github.com/aswathyseb/tincheck
Author: Aswathy Sebastian
Author-email: aswathyseb@gmail.com
Classifier: Programming Language :: Python :: 3
Classifier: License :: OSI Approved :: MIT License
Classifier: Operating System :: OS Independent
Requires-Python: >=3.6
Requires-Dist: plac
